octadatamlops/__init__.py
octadatamlops/main.py
octadatamlops-0.0.2.dist-info/LICENCE.txt
octadatamlops-0.0.2.dist-info/METADATA
octadatamlops-0.0.2.dist-info/WHEEL
octadatamlops-0.0.2.dist-info/top_level.txt
octadatamlops-0.0.2.dist-info/RECORD
